MANIFEST.in
README.md
requirements.txt
setup.cfg
setup.py
cloud_weather_report.egg-info/PKG-INFO
cloud_weather_report.egg-info/SOURCES.txt
cloud_weather_report.egg-info/dependency_links.txt
cloud_weather_report.egg-info/entry_points.txt
cloud_weather_report.egg-info/not-zip-safe
cloud_weather_report.egg-info/requires.txt
cloud_weather_report.egg-info/top_level.txt
cloudweatherreport/Makefile
cloudweatherreport/__init__.py
cloudweatherreport/cloud_weather_report.py
cloudweatherreport/reporter.py
cloudweatherreport/run.py
cloudweatherreport/utils.py
cloudweatherreport/examples/multi-test-plans.yaml
cloudweatherreport/examples/test-plan.yaml
cloudweatherreport/static/css/base.css
cloudweatherreport/static/css/ubuntu-styles.css
cloudweatherreport/static/images/error.svg
cloudweatherreport/static/images/line.svg
cloudweatherreport/static/images/pending.svg
cloudweatherreport/static/images/success.svg
cloudweatherreport/static/js/jquery.min.js
cloudweatherreport/templates/base.html
cloudweatherreport/tests/__init__.py
cloudweatherreport/tests/common_test.py
cloudweatherreport/tests/test_cloud_weather_report.py
cloudweatherreport/tests/test_reporter.py
cloudweatherreport/tests/test_run.py
cloudweatherreport/tests/test_utils.py