Metadata-Version: 1.0
Name: cloud-weather-report
Version: 0.4.1
Summary: Assess Juju charms and benchmarks on the clouds.
Home-page: https://github.com/juju-solutions/cloud-weather-report
Author: Juju Developers
Author-email: juju@lists.ubuntu.com
License: Affero GNU Public License v3
Platform: UNKNOWN
